kayle/__init__.py
kayle/match.py
kayle/ddragon/champions.py
kayle/ddragon/factory.py
kayle/ddragon/items.py
kayle/ddragon/maps.py
kayle/ddragon/pipeline.py
kayle/ddragon/runes.py
kayle/ddragon/summonerSpells.py
kayle/resources/summonersRiftAreas.png
kayle-0.5.46.dist-info/METADATA
kayle-0.5.46.dist-info/WHEEL
kayle-0.5.46.dist-info/top_level.txt
kayle-0.5.46.dist-info/RECORD
