Metadata-Version: 2.1
Name: kayle
Version: 0.5.46
Summary: Riot Games API Match wrapper for async requests
Home-page: https://github.com/Bcastet/camille
Author: Benjamin Castet
Author-email: benjamin.castet@gmail.com
License: BSD 2-clause
Requires-Dist: munch (==2.5.0)
Requires-Dist: pantheon (==2.0.0)
Requires-Dist: Pillow (==9.3.0)
Requires-Dist: pytest (==7.2.0)
Requires-Dist: requests (==2.28.1)
Requires-Dist: setuptools (==65.5.0)
